LICENSE
MANIFEST.in
README.md
setup.py
tailf/__init__.py
tailf/aio.py
tailf/base.py
tailf/basic.py
tailf/const.py
tailf.egg-info/PKG-INFO
tailf.egg-info/SOURCES.txt
tailf.egg-info/dependency_links.txt
tailf.egg-info/not-zip-safe
tailf.egg-info/top_level.txt
test/__init__.py
test/test_async.py
test/test_base.py
test/test_bench.py
test/test_internal_buffer.py
test/test_iter.py
test/test_read.py