Metadata-Version: 2.1
Name: tailf
Version: 0.3.1
Summary: tail -f functionality for your python code. Track file appends and truncations.
Home-page: http://gitlab.com/trooniee/tailf
Author: Sergei Shilovsky
Author-email: sshilovsky@gmail.com
License: MIT
Platform: UNKNOWN
Classifier: Development Status :: 3 - Alpha
Classifier: Intended Audience :: Developers
Classifier: License :: OSI Approved :: MIT License
Classifier: Operating System :: OS Independent
Classifier: Programming Language :: Python :: 3.6
Classifier: Programming Language :: Python :: 3.7
Classifier: Programming Language :: Python :: 3 :: Only
Classifier: Topic :: Software Development :: Libraries
Classifier: Topic :: Software Development :: Libraries :: Python Modules
